weboob/__init__.py
weboob/applications/__init__.py
weboob/applications/qbooblyrics/__init__.py
weboob/applications/qbooblyrics/main_window.py
weboob/applications/qbooblyrics/minisonglyrics.py
weboob/applications/qbooblyrics/qbooblyrics.py
weboob/applications/qbooblyrics/songlyrics.py
weboob/applications/qbooblyrics/ui/__init__.py
weboob/applications/qbooblyrics/ui/main_window_ui.py
weboob/applications/qbooblyrics/ui/minisonglyrics_ui.py
weboob/applications/qbooblyrics/ui/result_ui.py
weboob/applications/qbooblyrics/ui/songlyrics_ui.py
weboob/applications/qboobmsg/__init__.py
weboob/applications/qboobmsg/main_window.py
weboob/applications/qboobmsg/messages_manager.py
weboob/applications/qboobmsg/qboobmsg.py
weboob/applications/qboobmsg/ui/__init__.py
weboob/applications/qboobmsg/ui/main_window_ui.py
weboob/applications/qboobmsg/ui/messages_manager_ui.py
weboob/applications/qboobtracker/__init__.py
weboob/applications/qboobtracker/details.py
weboob/applications/qboobtracker/main_window.py
weboob/applications/qboobtracker/qboobtracker.py
weboob/applications/qboobtracker/ui/__init__.py
weboob/applications/qboobtracker/ui/details_ui.py
weboob/applications/qboobtracker/ui/main_window_ui.py
weboob/applications/qcineoob/__init__.py
weboob/applications/qcineoob/main_window.py
weboob/applications/qcineoob/minimovie.py
weboob/applications/qcineoob/miniperson.py
weboob/applications/qcineoob/minisubtitle.py
weboob/applications/qcineoob/minitorrent.py
weboob/applications/qcineoob/movie.py
weboob/applications/qcineoob/person.py
weboob/applications/qcineoob/qcineoob.py
weboob/applications/qcineoob/subtitle.py
weboob/applications/qcineoob/torrent.py
weboob/applications/qcineoob/ui/__init__.py
weboob/applications/qcineoob/ui/main_window_ui.py
weboob/applications/qcineoob/ui/minimovie_ui.py
weboob/applications/qcineoob/ui/miniperson_ui.py
weboob/applications/qcineoob/ui/minisubtitle_ui.py
weboob/applications/qcineoob/ui/minitorrent_ui.py
weboob/applications/qcineoob/ui/movie_ui.py
weboob_qt-2.0.dist-info/AUTHORS
weboob_qt-2.0.dist-info/COPYING
weboob_qt-2.0.dist-info/COPYING.LESSER
weboob_qt-2.0.dist-info/METADATA
weboob_qt-2.0.dist-info/WHEEL
weboob_qt-2.0.dist-info/entry_points.txt
weboob_qt-2.0.dist-info/top_level.txt
weboob_qt-2.0.dist-info/RECORD
